horqrux/__init__.py
horqrux/_misc.py
horqrux/analog.py
horqrux/api.py
horqrux/apply.py
horqrux/circuit.py
horqrux/matrices.py
horqrux/shots.py
horqrux/composite/__init__.py
horqrux/composite/compose.py
horqrux/composite/sequence.py
horqrux/differentiation/__init__.py
horqrux/differentiation/ad.py
horqrux/differentiation/adjoint.py
horqrux/differentiation/gpsr/__init__.py
horqrux/differentiation/gpsr/analytical.py
horqrux/differentiation/gpsr/gpsr_utils.py
horqrux/differentiation/gpsr/shots.py
horqrux/noise/__init__.py
horqrux/noise/noise.py
horqrux/noise/utils_noise.py
horqrux/primitives/__init__.py
horqrux/primitives/parametric.py
horqrux/primitives/primitive.py
horqrux/utils/__init__.py
horqrux/utils/conversion.py
horqrux/utils/operator_utils.py
horqrux/utils/sparse_utils.py
horqrux/utils/values_utils.py
horqrux-0.9.2.dist-info/METADATA
horqrux-0.9.2.dist-info/WHEEL
horqrux-0.9.2.dist-info/licenses/LICENSE
horqrux-0.9.2.dist-info/RECORD
