Metadata-Version: 2.4
Name: horqrux
Version: 0.9.2
Summary: Jax-based quantum state vector and noisy simulator.
Author-email: Gert-Jan Both <gert-jan.both@pasqal.com>, Dominik Seitz <dominik.seitz@pasqal.com>, Charles Moussa <charles.moussa@pasqal.com>
License: Apache 2.0
License-File: LICENSE
Classifier: License :: Other/Proprietary License
Classifier: Programming Language :: Python
Classifier: Programming Language :: Python :: 3
Classifier: Programming Language :: Python :: 3.9
Classifier: Programming Language :: Python :: 3.10
Classifier: Programming Language :: Python :: 3.11
Classifier: Programming Language :: Python :: 3.12
Classifier: Programming Language :: Python :: 3.13
Classifier: Programming Language :: Python :: Implementation :: CPython
Classifier: Programming Language :: Python :: Implementation :: PyPy
Requires-Python: >=3.8
Requires-Dist: chex
Requires-Dist: einops
Requires-Dist: flax
Requires-Dist: jax
Requires-Dist: jaxopt
Requires-Dist: numpy
Requires-Dist: optax
Provides-Extra: dev
Requires-Dist: black; extra == 'dev'
Requires-Dist: flake8; extra == 'dev'
Requires-Dist: mypy; extra == 'dev'
Requires-Dist: pre-commit; extra == 'dev'
Requires-Dist: pytest; extra == 'dev'
Requires-Dist: pytest-cov; extra == 'dev'
Requires-Dist: pytest-xdist; extra == 'dev'
Requires-Dist: ruff; extra == 'dev'
